my_codetest/__init__.py
my_codetest/fun_stuff.py
my_codetest-0.0.1.dist-info/METADATA
my_codetest-0.0.1.dist-info/WHEEL
my_codetest-0.0.1.dist-info/top_level.txt
my_codetest-0.0.1.dist-info/RECORD
