Metadata-Version: 2.1
Name: my-codetest
Version: 0.0.1
Summary: UNKNOWN
Home-page: UNKNOWN
Maintainer: Tobias Olsen
Maintainer-email: youremail@stats.ox.ac.uk
License: BSD 3-clause license
Platform: UNKNOWN
Requires-Dist: numpy
